{"name":"build-javascript","namedChunkGroups":{"polyfill":{"name":"polyfill","assets":[{"name":"webpack-runtime-3e6311a996d1b326e7ef.js","size":5665},{"name":"polyfill-3bdbde0a1391b4f1ccf9.js","size":85888}],"filteredAssets":0,"assetsSize":91553,"filteredAuxiliaryAssets":2,"auxiliaryAssetsSize":229564},"app":{"name":"app","assets":[{"name":"webpack-runtime-3e6311a996d1b326e7ef.js","size":5665},{"name":"framework-3509140eb02597508410.js","size":129792},{"name":"app-ac0942445b597d357da8.js","size":294336}],"filteredAssets":0,"assetsSize":429793,"filteredAuxiliaryAssets":3,"auxiliaryAssetsSize":1480624},"component---cache-caches-gatsby-plugin-offline-app-shell-js":{"name":"component---cache-caches-gatsby-plugin-offline-app-shell-js","assets":[{"name":"component---cache-caches-gatsby-plugin-offline-app-shell-js-f4d74fd61c5dd049377e.js","size":565}],"filteredAssets":0,"assetsSize":565,"filteredAuxiliaryAssets":1,"auxiliaryAssetsSize":1673},"component---src-pages-404-js":{"name":"component---src-pages-404-js","assets":[{"name":"styles.ab44448622e2ffc848c6.css","size":16049},{"name":"1bfc9850-a31de1f3436cf7c60e9f.js","size":2060},{"name":"b637e9a5-ad56ac6ef51e256dfedb.js","size":90144},{"name":"5e2a4920-df895caa23a90b01b2e6.js","size":647},{"name":"e6d51abba740d6a538b028339de2d2b070d23b1f-9a6fb170d3ae3d3cbc39.js","size":16307},{"name":"component---src-pages-404-js-d51163d2ab2eeaa4cf90.js","size":511}],"filteredAssets":0,"assetsSize":125718,"filteredAuxiliaryAssets":5,"auxiliaryAssetsSize":2249943},"component---src-pages-about-js":{"name":"component---src-pages-about-js","assets":[{"name":"styles.ab44448622e2ffc848c6.css","size":16049},{"name":"1bfc9850-a31de1f3436cf7c60e9f.js","size":2060},{"name":"b637e9a5-ad56ac6ef51e256dfedb.js","size":90144},{"name":"5e2a4920-df895caa23a90b01b2e6.js","size":647},{"name":"e6d51abba740d6a538b028339de2d2b070d23b1f-9a6fb170d3ae3d3cbc39.js","size":16307},{"name":"component---src-pages-about-js-2313a4b9756455f87f13.js","size":42468}],"filteredAssets":0,"assetsSize":167675,"filteredAuxiliaryAssets":5,"auxiliaryAssetsSize":2252981},"component---src-pages-index-js":{"name":"component---src-pages-index-js","assets":[{"name":"styles.ab44448622e2ffc848c6.css","size":16049},{"name":"1bfc9850-a31de1f3436cf7c60e9f.js","size":2060},{"name":"b637e9a5-ad56ac6ef51e256dfedb.js","size":90144},{"name":"5e2a4920-df895caa23a90b01b2e6.js","size":647},{"name":"e6d51abba740d6a538b028339de2d2b070d23b1f-9a6fb170d3ae3d3cbc39.js","size":16307},{"name":"component---src-pages-index-js-508a4a61571ce3c90d7c.js","size":75514}],"filteredAssets":0,"assetsSize":200721,"filteredAuxiliaryAssets":5,"auxiliaryAssetsSize":2389541},"component---src-pages-interests-js":{"name":"component---src-pages-interests-js","assets":[{"name":"styles.ab44448622e2ffc848c6.css","size":16049},{"name":"1bfc9850-a31de1f3436cf7c60e9f.js","size":2060},{"name":"b637e9a5-ad56ac6ef51e256dfedb.js","size":90144},{"name":"5e2a4920-df895caa23a90b01b2e6.js","size":647},{"name":"e6d51abba740d6a538b028339de2d2b070d23b1f-9a6fb170d3ae3d3cbc39.js","size":16307},{"name":"component---src-pages-interests-js-5a52c01ad18806412382.js","size":1805}],"filteredAssets":0,"assetsSize":127012,"filteredAuxiliaryAssets":5,"auxiliaryAssetsSize":2254942},"component---src-pages-works-js":{"name":"component---src-pages-works-js","assets":[{"name":"styles.ab44448622e2ffc848c6.css","size":16049},{"name":"1bfc9850-a31de1f3436cf7c60e9f.js","size":2060},{"name":"b637e9a5-ad56ac6ef51e256dfedb.js","size":90144},{"name":"5e2a4920-df895caa23a90b01b2e6.js","size":647},{"name":"e6d51abba740d6a538b028339de2d2b070d23b1f-9a6fb170d3ae3d3cbc39.js","size":16307},{"name":"component---src-pages-works-js-5725d5d3e44bb4672012.js","size":1715}],"filteredAssets":0,"assetsSize":126922,"filteredAuxiliaryAssets":5,"auxiliaryAssetsSize":2254516},"component---src-templates-work-detail-js":{"name":"component---src-templates-work-detail-js","assets":[{"name":"styles.ab44448622e2ffc848c6.css","size":16049},{"name":"1bfc9850-a31de1f3436cf7c60e9f.js","size":2060},{"name":"b637e9a5-ad56ac6ef51e256dfedb.js","size":90144},{"name":"5e2a4920-df895caa23a90b01b2e6.js","size":647},{"name":"e6d51abba740d6a538b028339de2d2b070d23b1f-9a6fb170d3ae3d3cbc39.js","size":16307},{"name":"component---src-templates-work-detail-js-89a81926bcc780781ebc.js","size":6212}],"filteredAssets":0,"assetsSize":131419,"filteredAuxiliaryAssets":5,"auxiliaryAssetsSize":2267915}},"assetsByChunkName":{"polyfill":["webpack-runtime-3e6311a996d1b326e7ef.js","polyfill-3bdbde0a1391b4f1ccf9.js"],"app":["webpack-runtime-3e6311a996d1b326e7ef.js","framework-3509140eb02597508410.js","app-ac0942445b597d357da8.js"],"component---cache-caches-gatsby-plugin-offline-app-shell-js":["component---cache-caches-gatsby-plugin-offline-app-shell-js-f4d74fd61c5dd049377e.js"],"component---src-pages-404-js":["styles.ab44448622e2ffc848c6.css","1bfc9850-a31de1f3436cf7c60e9f.js","b637e9a5-ad56ac6ef51e256dfedb.js","5e2a4920-df895caa23a90b01b2e6.js","e6d51abba740d6a538b028339de2d2b070d23b1f-9a6fb170d3ae3d3cbc39.js","component---src-pages-404-js-d51163d2ab2eeaa4cf90.js"],"component---src-pages-about-js":["styles.ab44448622e2ffc848c6.css","1bfc9850-a31de1f3436cf7c60e9f.js","b637e9a5-ad56ac6ef51e256dfedb.js","5e2a4920-df895caa23a90b01b2e6.js","e6d51abba740d6a538b028339de2d2b070d23b1f-9a6fb170d3ae3d3cbc39.js","component---src-pages-about-js-2313a4b9756455f87f13.js"],"component---src-pages-index-js":["styles.ab44448622e2ffc848c6.css","1bfc9850-a31de1f3436cf7c60e9f.js","b637e9a5-ad56ac6ef51e256dfedb.js","5e2a4920-df895caa23a90b01b2e6.js","e6d51abba740d6a538b028339de2d2b070d23b1f-9a6fb170d3ae3d3cbc39.js","component---src-pages-index-js-508a4a61571ce3c90d7c.js"],"component---src-pages-interests-js":["styles.ab44448622e2ffc848c6.css","1bfc9850-a31de1f3436cf7c60e9f.js","b637e9a5-ad56ac6ef51e256dfedb.js","5e2a4920-df895caa23a90b01b2e6.js","e6d51abba740d6a538b028339de2d2b070d23b1f-9a6fb170d3ae3d3cbc39.js","component---src-pages-interests-js-5a52c01ad18806412382.js"],"component---src-pages-works-js":["styles.ab44448622e2ffc848c6.css","1bfc9850-a31de1f3436cf7c60e9f.js","b637e9a5-ad56ac6ef51e256dfedb.js","5e2a4920-df895caa23a90b01b2e6.js","e6d51abba740d6a538b028339de2d2b070d23b1f-9a6fb170d3ae3d3cbc39.js","component---src-pages-works-js-5725d5d3e44bb4672012.js"],"component---src-templates-work-detail-js":["styles.ab44448622e2ffc848c6.css","1bfc9850-a31de1f3436cf7c60e9f.js","b637e9a5-ad56ac6ef51e256dfedb.js","5e2a4920-df895caa23a90b01b2e6.js","e6d51abba740d6a538b028339de2d2b070d23b1f-9a6fb170d3ae3d3cbc39.js","component---src-templates-work-detail-js-89a81926bcc780781ebc.js"]},"childAssetsByChunkName":{}}